Metadata-Version: 2.4
Name: agentica
Version: 1.2.6
Summary: AI Agent SDK
Home-page: https://github.com/shibing624/agentica
Author: XuMing
Author-email: xuming624@qq.com
License: Apache License 2.0
Keywords: Agentica,Agent Tool,action,agent,agentica
Classifier: Development Status :: 5 - Production/Stable
Classifier: Intended Audience :: Developers
Classifier: Intended Audience :: Education
Classifier: Intended Audience :: Science/Research
Classifier: License :: OSI Approved :: Apache Software License
Classifier: Operating System :: OS Independent
Classifier: Programming Language :: Python :: 3
Classifier: Programming Language :: Python :: 3.10
Classifier: Programming Language :: Python :: 3.11
Classifier: Programming Language :: Python :: 3.12
Classifier: Topic :: Scientific/Engineering :: Artificial Intelligence
Requires-Python: >=3.10.0
License-File: LICENSE
Requires-Dist: httpx
Requires-Dist: loguru
Requires-Dist: beautifulsoup4
Requires-Dist: openai
Requires-Dist: python-dotenv
Requires-Dist: pydantic
Requires-Dist: requests
Requires-Dist: sqlalchemy
Requires-Dist: scikit-learn
Requires-Dist: markdownify
Requires-Dist: tqdm
Requires-Dist: rich
Requires-Dist: pyyaml
Requires-Dist: mcp
Requires-Dist: puremagic
Requires-Dist: qdrant-client
Requires-Dist: langfuse
Requires-Dist: python-frontmatter
Dynamic: author
Dynamic: author-email
Dynamic: classifier
Dynamic: description
Dynamic: description-content-type
Dynamic: home-page
Dynamic: keywords
Dynamic: license
Dynamic: license-file
Dynamic: requires-dist
Dynamic: requires-python
Dynamic: summary
